autobahn_api/__init__.py
autobahn_api/cli.py
autobahn_api/data.py
autobahn_api/info.py
autobahn_api-1.0.6.dist-info/LICENSE
autobahn_api-1.0.6.dist-info/METADATA
autobahn_api-1.0.6.dist-info/WHEEL
autobahn_api-1.0.6.dist-info/entry_points.txt
autobahn_api-1.0.6.dist-info/top_level.txt
autobahn_api-1.0.6.dist-info/RECORD
