Metadata-Version: 2.1
Name: autobahn-api
Version: 1.0.6
Summary: Fetch data from the Autobahn API
Home-page: https://github.com/niftycode/autobahn-api
Author: Bodo Schönfeld
Author-email: bodo.schoenfeld@niftycode.de
License: MIT
Platform: any
Classifier: Intended Audience :: Developers
Classifier: License :: OSI Approved :: MIT License
Classifier: Operating System :: OS Independent
Classifier: Programming Language :: Python :: 3
Classifier: Programming Language :: Python :: 3.8
Classifier: Programming Language :: Python :: 3.9
Classifier: Programming Language :: Python :: 3.10
Classifier: Programming Language :: Python :: Implementation :: CPython
License-File: LICENSE
